emby_client/__init__.py
emby_client/api_client.py
emby_client/configuration.py
emby_client/rest.py
emby_client/api/__init__.py
emby_client/api/activity_log_service_api.py
emby_client/api/artists_service_api.py
emby_client/api/audio_service_api.py
emby_client/api/backup_api_api.py
emby_client/api/bif_service_api.py
emby_client/api/branding_service_api.py
emby_client/api/channel_service_api.py
emby_client/api/codec_parameter_service_api.py
emby_client/api/collection_service_api.py
emby_client/api/configuration_service_api.py
emby_client/api/connect_service_api.py
emby_client/api/device_service_api.py
emby_client/api/display_preferences_service_api.py
emby_client/api/dlna_server_service_api.py
emby_client/api/dlna_service_api.py
emby_client/api/dynamic_hls_service_api.py
emby_client/api/encoding_info_service_api.py
emby_client/api/environment_service_api.py
emby_client/api/feature_service_api.py
emby_client/api/ffmpeg_options_service_api.py
emby_client/api/game_genres_service_api.py
emby_client/api/generic_ui_api_service_api.py
emby_client/api/genres_service_api.py
emby_client/api/hls_segment_service_api.py
emby_client/api/image_service_api.py
emby_client/api/instant_mix_service_api.py
emby_client/api/item_lookup_service_api.py
emby_client/api/item_refresh_service_api.py
emby_client/api/item_update_service_api.py
emby_client/api/items_service_api.py
emby_client/api/library_service_api.py
emby_client/api/library_structure_service_api.py
emby_client/api/live_stream_service_api.py
emby_client/api/live_tv_service_api.py
emby_client/api/localization_service_api.py
emby_client/api/media_info_service_api.py
emby_client/api/movies_service_api.py
emby_client/api/music_genres_service_api.py
emby_client/api/notifications_service_api.py
emby_client/api/official_rating_service_api.py
emby_client/api/open_api_service_api.py
emby_client/api/package_service_api.py
emby_client/api/persons_service_api.py
emby_client/api/playlist_service_api.py
emby_client/api/playstate_service_api.py
embyclient-4.9.0.33.dist-info/METADATA
embyclient-4.9.0.33.dist-info/WHEEL
embyclient-4.9.0.33.dist-info/top_level.txt
embyclient-4.9.0.33.dist-info/RECORD
