Metadata-Version: 2.1
Name: embyclient
Version: 4.9.0.33
Summary: A Python client for Emby Media Server's API
Home-page: https://emby.media
Keywords: Emby,Rest,API,client,media,server,JSON
Classifier: Intended Audience :: Developers
Classifier: Topic :: Software Development :: Build Tools
Classifier: Topic :: Multimedia :: Video
Classifier: Topic :: Multimedia
Classifier: Topic :: Internet :: WWW/HTTP
Classifier: Operating System :: OS Independent
Requires-Dist: urllib3>=1.15
Requires-Dist: six>=1.10
Requires-Dist: certifi
Requires-Dist: python-dateutil
